LICENSE
MANIFEST.in
README.md
setup.py
shadow4_advanced/__init__.py
shadow4_advanced.egg-info/PKG-INFO
shadow4_advanced.egg-info/SOURCES.txt
shadow4_advanced.egg-info/dependency_links.txt
shadow4_advanced.egg-info/requires.txt
shadow4_advanced.egg-info/top_level.txt
shadow4_advanced/benders/__init__.py
shadow4_advanced/benders/s4_fixed_rods_bender_ellipsoid_mirror.py
shadow4_advanced/benders/s4_flexural_hinge_bender_ellipsoid_mirror.py
shadow4_advanced/fresnel_zone_plate/__init__.py
shadow4_advanced/fresnel_zone_plate/s4_fresnel_zone_plate.py
shadow4_advanced/hybrid/__init__.py
shadow4_advanced/hybrid/s4_hybrid_screen.py
shadow4_advanced/hybrid/__develop/hybrid_undulator_attributes.py
shadow4_advanced/hybrid/__develop/s4_hybrid_undulator.py