Metadata-Version: 2.4
Name: shadow4-advanced
Version: 0.0.16
Summary: advanced tools for shadow4 in python
Home-page: https://github.com/oasys-kit/shadow4-advanced/
Author: Manuel Sanchez del Rio, Luca Rebuffi, Xianbo Shi
Author-email: lrebuffi@anl.gov
License-File: LICENSE
Requires-Dist: setuptools
Requires-Dist: numpy
Requires-Dist: scipy
Requires-Dist: syned>=1.0.47
Requires-Dist: srxraylib>=1.0.63
Requires-Dist: wofryimpl>=1.0.33
Requires-Dist: shadow4>=0.1.67
Requires-Dist: shadow-hybrid-methods>=1.0.15
Dynamic: author
Dynamic: author-email
Dynamic: home-page
Dynamic: license-file
Dynamic: requires-dist
Dynamic: summary
